smartXML/__init__.py
smartXML/element.py
smartXML/xmltree.py
smartxml-1.1.7.dist-info/METADATA
smartxml-1.1.7.dist-info/WHEEL
smartxml-1.1.7.dist-info/top_level.txt
smartxml-1.1.7.dist-info/RECORD
