Metadata-Version: 2.4
Name: smartXML
Version: 1.1.7
Summary: smartXML package enables you to read, search, manipulate, and write XML files with ease
Author-email: Dudu Arbel <duduarbel@gmail.com>
License-Expression: MIT
Project-URL: Changelog, https://github.com/duduarbel/smartXML/blob/main/changelog.md
Keywords: python,example
Classifier: Programming Language :: Python :: 3
Classifier: Programming Language :: Python :: 3 :: Only
Classifier: Programming Language :: Python :: 3.9
Classifier: Programming Language :: Python :: 3.10
Classifier: Programming Language :: Python :: 3.11
Classifier: Programming Language :: Python :: 3.12
Classifier: Operating System :: OS Independent
Requires-Python: >=3.9
Requires-Dist: requests>=2.31
Provides-Extra: dev
Requires-Dist: pytest>=8.0; extra == "dev"
Requires-Dist: mypy>=1.8; extra == "dev"
Requires-Dist: ruff>=0.3; extra == "dev"
